yawebview/QtSingleApplication.py
yawebview/__init__.py
yawebview/sighandler.py
yawebview/webview.py
yawebview-0.2.7.dist-info/LICENSE
yawebview-0.2.7.dist-info/METADATA
yawebview-0.2.7.dist-info/WHEEL
yawebview-0.2.7.dist-info/top_level.txt
yawebview-0.2.7.dist-info/RECORD
